BREWasm/__init__.py
BREWasm/parser/__init__.py
BREWasm/parser/errors.py
BREWasm/parser/instruction.py
BREWasm/parser/leb128.py
BREWasm/parser/module.py
BREWasm/parser/opcodes.py
BREWasm/parser/opnames.py
BREWasm/parser/reader.py
BREWasm/parser/types.py
BREWasm/rewriter/BREWasm.py
BREWasm/rewriter/__init__.py
BREWasm/rewriter/defination.py
BREWasm/rewriter/indices_fixer.py
BREWasm/rewriter/modify_binary.py
BREWasm/rewriter/section_rewriter.py
BREWasm/rewriter/semantics_rewriter.py
BREWasm-1.0.6.data/data/images/Definition.png
BREWasm-1.0.6.dist-info/METADATA
BREWasm-1.0.6.dist-info/WHEEL
BREWasm-1.0.6.dist-info/top_level.txt
BREWasm-1.0.6.dist-info/RECORD
