Metadata-Version: 2.1
Name: BREWasm
Version: 1.0.6
Summary: A general purpose static binary rewriting framework for Wasm, which aims at reducing the complexity of the Wasm
Home-page: https://github.com/BREWasm/brewasm-project
Author: BREWasm
License: MIT
Keywords: BINARY,REWRITER,WASM
Requires-Dist: cyleb128
